{
  "name": "Adelaide Robinson",
  "age": 48,
  "address": {
    "street": "Vuho Mill",
    "city": "Raamkik",
    "state": "VT",
    "zip": "56987"
  },
  "contact": {
    "phone": "(476) 962-3121",
    "servicePhone": "800984527"
  },
  "birthday": "1992-11-20T10:45:46.072Z",
  "ip": "47.170.216.130",
  "foo": "bar",
  "profile": {
    "about": "Cappe gu cimpu cofkige catpe mew ziniphe ofsisek ubic ih gamuj vazep. Cimakbo fubponzu or kepeb teb hure covo havgecmog oju os lo owa punmazel diccarceh ciwuhere nocu fofrog. Oli pisos jeg tir wazase futi vog jadrotfu na ta jarce id. Amtejok evusajme lan pe ajkudrok mo fo ogwofkun racavu ir hogdohat cafo. Jac vew wer sicado bijdodhak ojtamtu osboom ji wi relciulo borwefav du. Osi zavgu dokigzo ka balag gur mi wiwdoh vuwhu ludnu nulcuzfop gal sohke.",
    "bio": "Fuklo zov fuhtug buder worozsij mumtu foskedeza ehnokhom muzveotu tegofo ehhizba ikovagped katimi hu zeno. Jobno cifosfab bobruepo pearu rusahzo wic ca hi no vagsicac div dav bowva jasfusa zizur haze. Deehmut wak hulalwuz cojubo gu ignascig duflan tir oru rocrov ih mud wasova cot bo vi normug vovrakpa. Se fa susiwite armushis eraciz rolja wahco ve suef so lidicep vokbuze ca luv nas ni. Tikfi cekiloh ovrid bu cule vaif pownenwim loma vemin kebiwacu imokiame vedukik nuvjod tug so. Lujoheh hiluma lij zezku nujusso wu labpa hanbihroz ed dalrocit oj lil iwo miweni dazposav jiepo sucap. Bija ujvo kerekco polzuzez ake osbo vu hafji loj ifdeliko pok hajza jes ju."
  },
  "apiKey": "1c65462b1e383a48d54bec6001cf17ab3f4dabd3c52c14c707212fe1c787f76e",
  "currency": {
    "code": "AED",
    "name": "United Arab Emirates Dirham"
  }
}