{
  "name": "Sylvia Harrison",
  "age": 28,
  "address": {
    "street": "Muel Path",
    "city": "Kasomel",
    "state": "WV",
    "zip": "02220"
  },
  "contact": {
    "phone": "(722) 263-3577",
    "servicePhone": "800983265"
  },
  "birthday": "1990-09-17T22:12:53.971Z",
  "ip": "238.11.196.70",
  "foo": "bar",
  "profile": {
    "about": "Do wifudrec abututim zezazu tiw kumezuba go tesdaowu caec govek zar wako taodi nejasa hotuke usonza linha ugobi. Dejsugu cupi pasdogfe ben ij gutzodak iruroihi jomhozoz ekipu viradwi ehhus jot ti ge muggepad. Pobwadse uha vidugin ifo ejeahepe mupcem fibteuci kudefu toc tipsa lamalef runhepbap. Jadma zeohoga joc pamuva jud efibuoh bovgoji gus sakimum wolut vawvot cipemi hagiafe kojmacip muzruve bishun dazgevdej kinokudo. Bepkuruc cajafage rigebger fenlikic tij cu afnuvvaj ret kejnigoh me hu id. Cimduw we pudu rudza be fon jestol ebehaju tigzat vo ubifujmag wahra husa. Pus fukisjen tabodfig tusu fajohe haizlot sucpar hezu ajse esunva sumav siamo.",
    "bio": "Agecvi giar tuibnu az onaces ecocagob mepim gedfebod janhot dume zuh ducmu ha. Fonin emwavo voicudo ejiullut hofwivhuw ojsi vebedsar alesuwci peg lomcow muvar uso nomiv fiweda laroma zunmikmo nekus. Ip zucwo weruhjom od mu ugu wuw ibuad vurasmo fol erhuw la hidfi zi zattat nes mef akoge. Pamdeeb uz nonavve buwbiwud ge bi akucazdim zebew ohace oz dimbommu cogbudon. Dimpuupi wafra uwa bazka ciz juwhowi abe hupef seek titli le gewuro. Ikamidgu cebiz jis da baome jijisez lu ampuci mok libdako otinis epuil eftigdul uli da towlo. Gop abnov en gepamala dogkumnun torfuvab irasuimi veiwsam seja gofgowtu vutjuspi waor fovoh."
  },
  "apiKey": "fca67ef21b766adab467d9ac49469d7effdf9d1ff349343e335fd4040537c361",
  "currency": {
    "code": "RSD",
    "name": "Serbia Dinar"
  }
}